mapstorch/__init__.py
mapstorch/bkg.py
mapstorch/constant.py
mapstorch/default.py
mapstorch/io.py
mapstorch/map.py
mapstorch/opt.py
mapstorch/plot.py
mapstorch/util.py
mapstorch/reference/henke.xdr
mapstorch/reference/xrf_library.csv
mapstorch-0.0.1.dist-info/LICENSE
mapstorch-0.0.1.dist-info/METADATA
mapstorch-0.0.1.dist-info/WHEEL
mapstorch-0.0.1.dist-info/top_level.txt
mapstorch-0.0.1.dist-info/RECORD
