Metadata-Version: 2.1
Name: mapstorch
Version: 0.0.1
Summary: A differentiable modeling package for automating X-ray fluorescence (XRF) analysis
Home-page: https://github.com/xyin-anl/MapsTorch
Author: Xiangyu Yin
Author-email: xyin@anl.gov
Classifier: Programming Language :: Python :: 3
Classifier: Operating System :: OS Independent
Requires-Python: >=3.7
License-File: LICENSE
Requires-Dist: h5py
Requires-Dist: tqdm
Requires-Dist: numpy<2.0.0
Requires-Dist: scipy
Requires-Dist: pandas
Requires-Dist: matplotlib
Requires-Dist: anywidget
Requires-Dist: plotly
Requires-Dist: marimo
Requires-Dist: torch
